config/__init__.py
config/config.py
zim/__init__.py
zim/automatic_mask_generator.py
zim/build_model.py
zim/predictor.py
zim/modeling/__init__.py
zim/modeling/decoder.py
zim/modeling/encoder.py
zim/modeling/zim.py
zim/utils/__init__.py
zim/utils/amg.py
zim/utils/argparser.py
zim/utils/print.py
zim/utils/utils.py
zero_shot_image_matting-0.1.dist-info/LICENSE
zero_shot_image_matting-0.1.dist-info/METADATA
zero_shot_image_matting-0.1.dist-info/NOTICE
zero_shot_image_matting-0.1.dist-info/WHEEL
zero_shot_image_matting-0.1.dist-info/top_level.txt
zero_shot_image_matting-0.1.dist-info/RECORD
